<annotation>
	<folder>20180602</folder>
	<filename>bbs (128).jpg</filename>
	<path>/home/hope/Drone_label/20180602/bbs (128).jpg</path>
	<source>
		<database>Unknown</database>
	</source>
	<size>
		<width>640</width>
		<height>368</height>
		<depth>3</depth>
	</size>
	<segmented>0</segmented>
	<object>
		<name>drone</name>
		<pose>Unspecified</pose>
		<truncated>0</truncated>
		<difficult>0</difficult>
		<bndbox>
			<xmin>188</xmin>
			<ymin>13</ymin>
			<xmax>293</xmax>
			<ymax>66</ymax>
		</bndbox>
	</object>
	<object>
		<name>person</name>
		<pose>Unspecified</pose>
		<truncated>1</truncated>
		<difficult>0</difficult>
		<bndbox>
			<xmin>129</xmin>
			<ymin>175</ymin>
			<xmax>197</xmax>
			<ymax>368</ymax>
		</bndbox>
	</object>
</annotation>
