<annotation>
   <filename>bing (115).jpg</filename>
   <path>/home/zheng/ESDC_2018/drone-detection-image-set/internet/20180524/bing (115).jpg</path>
   <source>
      <database>Unknow</database>
   </source>
   <size>
      <width>512</width>
      <height>341</height>
      <depth>3</depth>
   </size>
   <segmented>0</segmented>
   <object>
      <name>drone</name>
      <pose>Unspecified</pose>
      <truncated>0</truncated>
      <difficult>0</difficult>
      <bndbox>
         <xmin>176</xmin>
         <ymin>143</ymin>
         <xmax>315</xmax>
         <ymax>198</ymax>
      </bndbox>
   </object>
</annotation>
